Metadata-Version: 2.1
Name: pytorch-influence-functions
Version: 0.1.1
Summary: This package is a plug-n-play PyTorch reimplementation of Influence Functions. Influence Functions were introduced in the paper Understanding Black-box Predictions via Influence Functions by Pang Wei Koh and Percy Liang (ICML2017).
Home-page: https://github.com/nimarb/pytorch_influence_functions
Author: Nimar Blume
Author-email: l.nimar.b@gmail.com
License: UNKNOWN
Platform: UNKNOWN
Classifier: Development Status :: 3 - Alpha
Classifier: Intended Audience :: Science/Research
Classifier: License :: OSI Approved :: GNU General Public License (GPL)
Classifier: Programming Language :: Python :: 3
Classifier: Topic :: Scientific/Engineering :: Artificial Intelligence
Classifier: Topic :: Scientific/Engineering :: Mathematics
Classifier: Operating System :: POSIX :: Linux
Classifier: Operating System :: MacOS
Classifier: Operating System :: Microsoft :: Windows
Classifier: Operating System :: POSIX
Classifier: Operating System :: OS Independent
Requires-Python: >=3.6
